{
    "USDCUSDT": {
        "price": 0.9999,
        "time": "2025-02-16T11:00:28.077623",
        "trailing_stop_active": false,
        "highest_price": null
    },
    "SLFUSDT": {
        "price": 0.2214,
        "time": "2025-02-16T11:00:40.079689",
        "trailing_stop_active": false,
        "highest_price": null
    },
    "ARKUSDT": {
        "price": 0.3987,
        "time": "2025-02-16T14:01:12.921233",
        "trailing_stop_active": false,
        "highest_price": null
    },
    "GLMUSDT": {
        "price": 0.3587,
        "time": "2025-02-16T14:32:38.984864",
        "trailing_stop_active": false,
        "highest_price": null
    },
    "POLYXUSDT": {
        "price": 0.1895,
        "time": "2025-02-16T14:32:51.111915",
        "trailing_stop_active": false,
        "highest_price": null
    },
    "POWRUSDT": {
        "price": 0.2217,
        "time": "2025-02-16T14:32:51.918020",
        "trailing_stop_active": false,
        "highest_price": null
    },
    "ELFUSDT": {
        "price": 0.3043,
        "time": "2025-02-16T15:24:10.651422",
        "trailing_stop_active": false,
        "highest_price": null
    },
    "ACHUSDT": {
        "price": 0.028,
        "time": "2025-02-16T18:01:21.397497",
        "trailing_stop_active": false,
        "highest_price": null
    },
    "TRXUSDT": {
        "price": 0.2427,
        "time": "2025-02-16T19:00:52.250271",
        "trailing_stop_active": false,
        "highest_price": null
    },
    "CAKEUSDT": {
        "price": 2.865,
        "time": "2025-02-16T20:00:56.890571",
        "trailing_stop_active": false,
        "highest_price": null
    },
    "SPELLUSDT": {
        "price": 0.000987,
        "time": "2025-02-16T20:25:33.966598",
        "trailing_stop_active": false,
        "highest_price": null
    },
    "BARUSDT": {
        "price": 1.85,
        "time": "2025-02-16T20:31:29.478738",
        "trailing_stop_active": false,
        "highest_price": null
    }
}