{
    "BNBUSDT": {
        "price": 672.33,
        "time": "2025-02-22T18:45:48.369750"
    },
    "SUIUSDT": {
        "price": 3.4295,
        "time": "2025-02-22T18:45:48.808261"
    },
    "PNUTUSDT": {
        "price": 0.2053,
        "time": "2025-02-22T18:45:49.276291"
    },
    "RUNEUSDT": {
        "price": 1.385,
        "time": "2025-02-22T18:45:49.423005"
    },
    "WIFUSDT": {
        "price": 0.696,
        "time": "2025-02-22T18:45:49.675139"
    },
    "NEARUSDT": {
        "price": 3.527,
        "time": "2025-02-22T18:45:50.421416"
    },
    "NEIROUSDT": {
        "price": 0.00041033,
        "time": "2025-02-22T18:45:50.586068"
    },
    "ACTUSDT": {
        "price": 0.2019,
        "time": "2025-02-22T18:45:50.749872"
    },
    "SOLVUSDT": {
        "price": 0.0371,
        "time": "2025-02-22T18:45:51.179735"
    },
    "ETHFIUSDT": {
        "price": 1.173,
        "time": "2025-02-22T18:45:52.520990"
    },
    "BIOUSDT": {
        "price": 0.1353,
        "time": "2025-02-22T18:45:53.144883"
    },
    "NOTUSDT": {
        "price": 0.003029,
        "time": "2025-02-22T18:45:53.330282"
    },
    "PENDLEUSDT": {
        "price": 3.521,
        "time": "2025-02-22T18:45:53.615726"
    },
    "MEUSDT": {
        "price": 1.535,
        "time": "2025-02-22T18:45:54.193529"
    },
    "DUSDT": {
        "price": 0.08931,
        "time": "2025-02-22T18:45:54.331236"
    },
    "TURBOUSDT": {
        "price": 0.003836,
        "time": "2025-02-22T18:45:54.478129"
    },
    "ATOMUSDT": {
        "price": 4.967,
        "time": "2025-02-22T18:45:54.627376"
    },
    "COOKIEUSDT": {
        "price": 0.2316,
        "time": "2025-02-22T18:45:55.635670"
    },
    "APEUSDT": {
        "price": 0.731,
        "time": "2025-02-22T18:45:56.068233"
    },
    "ICPUSDT": {
        "price": 7.255,
        "time": "2025-02-22T18:45:56.576497"
    },
    "DYDXUSDT": {
        "price": 0.8079,
        "time": "2025-02-22T18:45:56.746789"
    },
    "STPTUSDT": {
        "price": 0.09938,
        "time": "2025-02-22T18:45:57.130489"
    },
    "1000CHEEMSUSDT": {
        "price": 0.001027,
        "time": "2025-02-22T18:45:57.276143"
    },
    "GMTUSDT": {
        "price": 0.0711,
        "time": "2025-02-22T18:45:57.943356"
    },
    "IOUSDT": {
        "price": 1.421,
        "time": "2025-02-22T18:45:59.726685"
    },
    "BLURUSDT": {
        "price": 0.1511,
        "time": "2025-02-22T18:46:00.210311"
    },
    "1000SATSUSDT": {
        "price": 0.0001274,
        "time": "2025-02-22T18:46:00.419596"
    },
    "BBUSDT": {
        "price": 0.1726,
        "time": "2025-02-22T18:46:00.651772"
    },
    "EOSUSDT": {
        "price": 0.6499,
        "time": "2025-02-22T18:46:01.091942"
    },
    "AVAUSDT": {
        "price": 0.7028,
        "time": "2025-02-22T18:46:01.232712"
    },
    "MANTAUSDT": {
        "price": 0.407,
        "time": "2025-02-22T18:46:01.515299"
    },
    "RSRUSDT": {
        "price": 0.008792,
        "time": "2025-02-22T18:46:01.814045"
    },
    "ENSUSDT": {
        "price": 27.45,
        "time": "2025-02-22T18:46:01.964661"
    },
    "PEOPLEUSDT": {
        "price": 0.0219,
        "time": "2025-02-22T18:46:02.090397"
    },
    "STRKUSDT": {
        "price": 0.235,
        "time": "2025-02-22T18:46:02.574648"
    }
}